oscal_pydantic/__init__.py
oscal_pydantic/catalog.py
oscal_pydantic/document.py
oscal_pydantic/profile.py
oscal_pydantic/py.typed
oscal_pydantic/core/__init__.py
oscal_pydantic/core/base.py
oscal_pydantic/core/common.py
oscal_pydantic/core/datatypes.py
oscal_pydantic/core/decorators.py
oscal_pydantic/core/py.typed
oscal_pydantic/core/properties/__init__.py
oscal_pydantic/core/properties/base_property.py
oscal_pydantic/core/properties/oscal_properties.py
oscal_pydantic/core/properties/rmf_properties.py
oscal_pydantic_v2-2024.3.20.dist-info/LICENSE
oscal_pydantic_v2-2024.3.20.dist-info/METADATA
oscal_pydantic_v2-2024.3.20.dist-info/WHEEL
oscal_pydantic_v2-2024.3.20.dist-info/top_level.txt
oscal_pydantic_v2-2024.3.20.dist-info/RECORD
