Metadata-Version: 2.1
Name: oscal-pydantic-v2
Version: 2024.3.20
Summary: A set of Pydantic models generated from the OSCAL specification.
Author-email: Robert Sherwood <robert.sherwood@credentive.com>
License: oscal-pydantic-v2 by Robert Sherwood is marked with CC0 1.0. To view a copy of this license, visit http://creativecommons.org/publicdomain/zero/1.0
Project-URL: Homepage, https://github.com/RS-Credentive/oscal-pydantic
Keywords: oscal,OSCAL,pydantic
Requires-Python: >=3.10
License-File: LICENSE
Requires-Dist: annotated-types
Requires-Dist: dnspython >=2.3
Requires-Dist: email-validator >=2
Requires-Dist: idna >=3.4
Requires-Dist: pydantic >=2
Requires-Dist: pydantic-core >=2
Requires-Dist: typing-extensions
